cleverapi/__init__.py
cleverapi/action.py
cleverapi/clever_api.py
cleverapi/clever_longpoll.py
cleverapi/connector.py
cleverapi/exceptions.py
cleverapi/extension/__init__.py
cleverapi/extension/clever_auth.py
cleverapi-0.3.4.dist-info/DESCRIPTION.rst
cleverapi-0.3.4.dist-info/METADATA
cleverapi-0.3.4.dist-info/RECORD
cleverapi-0.3.4.dist-info/WHEEL
cleverapi-0.3.4.dist-info/metadata.json
cleverapi-0.3.4.dist-info/top_level.txt
