Metadata-Version: 2.0
Name: cleverapi
Version: 0.3.4
Summary: Python Clever Api
Home-page: https://github.com/oncecreated/cleverapi
Author: Oncecreated
License: UNKNOWN
Platform: UNKNOWN
Classifier: Programming Language :: Python :: 3.6
Classifier: License :: OSI Approved :: MIT License
Classifier: Operating System :: OS Independent
Requires-Dist: aiohttp
Requires-Dist: requests
